pybotlib/__init__.py
pybotlib/exceptions/__init__.py
pybotlib/utils/__init__.py
pybotlib-0.1.5.dist-info/LICENSE
pybotlib-0.1.5.dist-info/METADATA
pybotlib-0.1.5.dist-info/WHEEL
pybotlib-0.1.5.dist-info/top_level.txt
pybotlib-0.1.5.dist-info/RECORD
